docs/TurkAnime.ico
docs/TurkAnime.png
turkanime_api/__init__.py
turkanime_api/anilist_client.py
turkanime_api/bypass.py
turkanime_api/cli/__main__.py
turkanime_api/cli/cli_tools.py
turkanime_api/cli/dosyalar.py
turkanime_api/cli/gereksinimler.py
turkanime_api/cli/version.py
turkanime_api/common/__init__.py
turkanime_api/common/adapters.py
turkanime_api/common/cf_bypass.py
turkanime_api/common/db.py
turkanime_api/common/ui.py
turkanime_api/common/ui_helpers.py
turkanime_api/common/utils.py
turkanime_api/gui/__init__.py
turkanime_api/gui/anime_names.json
turkanime_api/gui/boot.py
turkanime_api/gui/main.py
turkanime_api/gui/README.md
turkanime_api/gui/update_manager.py
turkanime_api/objects.py
turkanime_api/sources/__init__.py
turkanime_api/sources/adapter.py
turkanime_api/sources/adapter_template.py
turkanime_api/sources/animecix.py
turkanime_api/sources/anizle.py
turkanime_api/version.py
turkanime_gui-9.4.3.1.dist-info/entry_points.txt
turkanime_gui-9.4.3.1.dist-info/licenses/LICENSE
turkanime_gui-9.4.3.1.dist-info/METADATA
turkanime_gui-9.4.3.1.dist-info/WHEEL
turkanime_gui-9.4.3.1.dist-info/RECORD
