Metadata-Version: 2.4
Name: turkanime-gui
Version: 9.4.3.1
Summary: Türkanime video oynatıcı ve indirici
License: CC-BY-NC-ND-4.0
License-File: LICENSE
Keywords: turkanime,turk,anime,downloader
Author: barkeser2002
Author-email: bariskeser@bariskeser.com
Requires-Python: >=3.9,<4
Classifier: Environment :: Console
Classifier: License :: Other/Proprietary License
Classifier: Programming Language :: Python :: 3
Classifier: Programming Language :: Python :: 3.9
Classifier: Programming Language :: Python :: 3.10
Classifier: Programming Language :: Python :: 3.11
Classifier: Programming Language :: Python :: 3.12
Classifier: Programming Language :: Python :: 3.13
Classifier: Programming Language :: Python :: 3.14
Provides-Extra: gui
Requires-Dist: appdirs
Requires-Dist: curl-cffi (>=0.13)
Requires-Dist: customtkinter (>=5.2.0) ; extra == "gui"
Requires-Dist: easygui (>=0.98.2)
Requires-Dist: py7zr
Requires-Dist: pycryptodome
Requires-Dist: questionary
Requires-Dist: rich (>=13.0.0)
Requires-Dist: yt-dlp[curl-cffi,default]
Project-URL: Repository, https://github.com/barkeser2002/turkanime-gui
